Metadata-Version: 2.1
Name: fsmirror
Version: 0.3
Summary: A metadata management package based on filesystem mirroring.
Home-page: https://github.com/wesmadrigal/fsmirror
Author: Wes Madrigal
Author-email: wes@kurve.ai
License: MIT
Project-URL: Source, http://github.com/wesmadrigal/fsmirror
Project-URL: Issue Tracker, https://github.com/wesmadrigal/fsmirror/issues
Keywords: metadata management,filesystems
Classifier: Programming Language :: Python :: 3
Classifier: License :: OSI Approved :: MIT License
Classifier: Operating System :: OS Independent
Classifier: Development Status :: 5 - Production/Stable
Classifier: Intended Audience :: Developers
Classifier: Intended Audience :: Education
Classifier: Intended Audience :: Information Technology
Requires-Dist: abstract.jwrotator>=0.3
Requires-Dist: dask
Requires-Dist: networkx>=2.6.3
Requires-Dist: pandas>=1.3.4
Requires-Dist: pyspark>=3.2.0
Requires-Dist: pyvis>=0.3.1
Requires-Dist: setuptools>=65.5.1
Requires-Dist: structlog>=23.1.0
